terraform_ci/__init__.py
terraform_ci/ci_runner.py
terraform_ci/install_terraform.py
terraform_ci/post_plan.py
terraform_ci/sectionless_configparser.py
terraform_ci/terraform_cd.py
terraform_ci-1.3.1.dist-info/METADATA
terraform_ci-1.3.1.dist-info/WHEEL
terraform_ci-1.3.1.dist-info/entry_points.txt
terraform_ci-1.3.1.dist-info/top_level.txt
terraform_ci-1.3.1.dist-info/RECORD
