Metadata-Version: 2.1
Name: terraform-ci
Version: 1.3.1
Summary: Terraform CI runs terraform in Travis-CI
Home-page: https://github.com/twindb/terraform-ci
Author: TwinDB
Author-email: dev@twindb.com
License: Apache Software License 2.0
Platform: UNKNOWN
Classifier: Development Status :: 5 - Production/Stable
Classifier: Environment :: Console
Classifier: Intended Audience :: Developers
Classifier: License :: OSI Approved :: Apache Software License
Classifier: Natural Language :: English
Classifier: Operating System :: POSIX :: Linux
Classifier: Programming Language :: Python :: 3
Classifier: Programming Language :: Python :: 3.6
Classifier: Programming Language :: Python :: 3.7
Requires-Python: >=3.6
Requires-Dist: boto3 (~=1.10)
Requires-Dist: botocore (>=1.13.46)
Requires-Dist: Click (~=7.0)
Requires-Dist: PyGithub (~=1.45)
Requires-Dist: pyhcl (~=0.3)
Requires-Dist: requests (~=2.22)
